deepmreye/__init__.py
deepmreye/_version.py
deepmreye/analyse.py
deepmreye/architecture.py
deepmreye/preprocess.py
deepmreye/train.py
deepmreye/masks/dme_template.nii
deepmreye/masks/eyemask_big.nii
deepmreye/masks/eyemask_small.nii
deepmreye/util/__init__.py
deepmreye/util/data_generator.py
deepmreye/util/data_io.py
deepmreye/util/model_opts.py
deepmreye/util/util.py
deepmreye-0.3.dist-info/METADATA
deepmreye-0.3.dist-info/WHEEL
deepmreye-0.3.dist-info/licenses/LICENSE
deepmreye-0.3.dist-info/RECORD
