Metadata-Version: 2.4
Name: deepmreye
Version: 0.3
Summary: MR-based eye tracker without eye tracking
Project-URL: home, https://github.com/DeepMReye/DeepMReye
Author-email:  Markus Frey <markus.frey1@gmail.com>
Maintainer-email:  Markus Frey <markus.frey1@gmail.com>
License:                    GNU LESSER GENERAL PUBLIC LICENSE
License-File: LICENSE
Classifier: Development Status :: 3 - Alpha
Classifier: Intended Audience :: Science/Research
Classifier: License :: OSI Approved :: GNU Lesser General Public License v3 (LGPLv3)
Classifier: Programming Language :: Python
Classifier: Programming Language :: Python :: 3
Requires-Python: <3.12,>=3.9.0
Requires-Dist: antspyx
Requires-Dist: plotly
Requires-Dist: scikit-learn
Requires-Dist: tensorflow==2.15.0
Provides-Extra: all
Requires-Dist: pytest-cov; extra == 'all'
Requires-Dist: pytest>6; extra == 'all'
Requires-Dist: sphinx-argparse; extra == 'all'
Requires-Dist: sphinx-rtd-theme; extra == 'all'
Requires-Dist: sphinx>=2.0; extra == 'all'
Requires-Dist: tox; extra == 'all'
Provides-Extra: doc
Requires-Dist: sphinx-argparse; extra == 'doc'
Requires-Dist: sphinx-rtd-theme; extra == 'doc'
Requires-Dist: sphinx>=2.0; extra == 'doc'
Provides-Extra: docs
Requires-Dist: sphinx-argparse; extra == 'docs'
Requires-Dist: sphinx-rtd-theme; extra == 'docs'
Requires-Dist: sphinx>=2.0; extra == 'docs'
Provides-Extra: streamlit
Requires-Dist: streamlit; extra == 'streamlit'
Provides-Extra: style
Requires-Dist: tox; extra == 'style'
Provides-Extra: test
Requires-Dist: pytest-cov; extra == 'test'
Requires-Dist: pytest>6; extra == 'test'
Provides-Extra: tests
Requires-Dist: pytest-cov; extra == 'tests'
Requires-Dist: pytest>6; extra == 'tests'
